{"name":"searchBySingleKeyword","id":"starter.wikipedia.WhenSearchingForTerms:searchBySingleKeyword","testCaseName":"starter.wikipedia.WhenSearchingForTerms","testSteps":[{"number":1,"description":"Navigate to the home page","duration":7514,"startTime":"2022-09-07T01:09:02.276449920Z[Etc/UTC]","screenshots":[{"screenshot":"2fce739fafa47379f791901048340cb0aff8dea2ba341b44405c1602c71d7d27.png","timeStamp":1662512949790,"screenshotName":"2fce739fafa47379f791901048340cb0aff8dea2ba341b44405c1602c71d7d27.png"}],"result":"SUCCESS","precondition":false,"level":0},{"number":2,"description":"Search by keyword \u0027Everest\u0027","duration":1167,"startTime":"2022-09-07T01:09:09.795471275Z[Etc/UTC]","screenshots":[{"screenshot":"d9e13ccdfeac4f17eaee7d22c59fd541588f74f9c76975da2b67a28738fba6ec.png","timeStamp":1662512950962,"screenshotName":"d9e13ccdfeac4f17eaee7d22c59fd541588f74f9c76975da2b67a28738fba6ec.png"}],"result":"SUCCESS","precondition":false,"level":0},{"number":3,"description":"The first heading should be \u0027Mount Everest\u0027","duration":201,"startTime":"2022-09-07T01:09:10.963471517Z[Etc/UTC]","screenshots":[{"screenshot":"cad0a5d1854066fa05d2ad970cbac1c78b6e88297acaa8f34b6bf334bad2111f.png","timeStamp":1662512951164,"screenshotName":"cad0a5d1854066fa05d2ad970cbac1c78b6e88297acaa8f34b6bf334bad2111f.png"}],"result":"SUCCESS","precondition":false,"level":0}],"userStory":{"id":"starter.wikipedia.WhenSearchingForTerms","storyName":"When searching for terms","displayName":"When searching for terms","storyClassName":"starter.wikipedia.WhenSearchingForTerms","path":"wikipedia","type":"story"},"featureTag":{"name":"Wikipedia/When searching for terms","type":"story","displayName":"Wikipedia/When searching for terms"},"title":"Search by single keyword","tags":[{"name":"Wikipedia/When searching for terms","type":"story","displayName":"Wikipedia/When searching for terms"},{"name":"Wikipedia","type":"feature","displayName":"Wikipedia"}],"startTime":"2022-09-07T01:09:01.631149463Z[Etc/UTC]","duration":9541,"projectKey":"","sessionId":"5d2412d1e2a4250e3dd55c09834cfdd1","driver":"chrome","isManualTestingUpToDate":false,"manual":false,"testSource":"JUnit5","order":0,"result":"SUCCESS"}